{
  "slug": "도급계약서",
  "title": "2026 도급계약서 양식 무료 다운로드 (HWP, PDF, Word)",
  "shortTitle": "도급계약서",
  "description": "일의 완성을 약속하고 그 결과에 대해 대가를 지급하는 계약이에요. 건설, 인테리어, 제조업에서 많이 사용해요.",
  "category": "법률·계약",
  "source": "법무부",
  "sourceUrl": "https://www.moj.go.kr",
  "downloads": {},
  "downloadNames": {},
  "previewDataKey": "도급계약서_DATA",
  "relatedArticle": "/w/용역계약서-차이",
  "relatedDocs": [
    {
      "title": "대리점계약서 양식",
      "url": "/forms/대리점계약서"
    },
    {
      "title": "매매계약서 양식",
      "url": "/forms/매매계약서"
    },
    {
      "title": "견적서 양식",
      "url": "/forms/견적서"
    },
    {
      "title": "세금계산서 양식",
      "url": "/forms/세금계산서"
    },
    {
      "title": "하자보수 청구 방법",
      "url": "/w/하자보수-청구"
    }
  ],
  "tips": [
    "완성 기한과 인도 장소를 명확히 정해야 해요",
    "하자 보수 기간과 책임 범위를 특약사항에 넣으세요",
    "공사 대금 지급 시기(착수금, 중도금, 준공금)를 명시하세요"
  ],
  "faq": [
    {
      "question": "도급과 용역 차이는?",
      "answer": "도급은 '결과물 완성'에 초점을 두고, 용역은 '노무 제공' 자체에 초점을 둬요. 도급은 완성하지 못하면 대금 청구가 어려워요."
    },
    {
      "question": "도급 완성 후 하자 발견하면?",
      "answer": "계약서에 하자 보수 기간(보통 1~2년)이 있으면 무상 수리를 요구할 수 있어요. 기간이 지나면 민법상 하자담보책임을 주장할 수 있어요."
    },
    {
      "question": "도급인이 중간에 계약 해지하면?",
      "answer": "도급인은 언제든 해지 가능하지만, 수급인이 이미 한 일에 대해서는 대금을 지급하고 손해를 배상해야 해요."
    }
  ],
  "createdAt": "2026-01-17",
  "externalDownload": {
    "source": "프리폼",
    "url": "https://www.freeforms.co.kr/search/?q=도급계약서",
    "description": "프리폼에서 무료 다운로드"
  }
}