{
  "slug": "매도청구서",
  "title": "2026 매도청구서 양식 무료 다운로드 (HWP, PDF, Word)",
  "shortTitle": "매도청구서",
  "description": "공동 소유 부동산 중 자기 지분만 팔고 싶을 때 다른 공유자에게 보내는 서류예요.",
  "category": "상속·가족",
  "source": "법무부",
  "sourceUrl": "https://www.moj.go.kr",
  "downloads": {},
  "downloadNames": {},
  "previewDataKey": "매도청구서_DATA",
  "relatedArticle": "/w/공유물-분할",
  "relatedDocs": [
    { "title": "매매계약서 양식", "url": "/forms/매매계약서" },
    { "title": "내용증명 양식", "url": "/forms/내용증명" },
    { "title": "합의서 양식", "url": "/forms/합의서" },
    { "title": "임대차계약서 양식", "url": "/forms/임대차계약서" },
    { "title": "공유물분할 방법", "url": "/w/공유물-분할" }
  ],
  "tips": [
    "시가 감정평가서 첨부하면 설득력 높아져요. 임의 가격은 분쟁 생겨요.",
    "내용증명으로 발송해서 수령 증거 남기세요.",
    "상대방이 거부하면 법원에 공유물분할청구 소송 가능해요."
  ],
  "faq": [
    {
      "question": "상대방이 안 사겠다고 하면요?",
      "answer": "법원에 공유물분할청구 소송하면 돼요. 경매로 나눠질 수 있어요."
    },
    {
      "question": "가격은 어떻게 정하나요?",
      "answer": "감정평가 받거나 실거래가 참고하세요. 임의로 정하면 나중에 문제돼요."
    },
    {
      "question": "매도청구 거절당하면요?",
      "answer": "소송으로 가면 법원이 강제로 분할해줘요. 경매 통해 현금화될 수도 있어요."
    }
  ],
  "createdAt": "2026-01-17"
}