{
  "slug": "병적증명서신청서",
  "title": "2026 병적증명서신청서 양식 무료 다운로드 (HWP, PDF, Word)",
  "shortTitle": "병적증명서신청서",
  "description": "군복무 기록을 확인하는 서류 신청서예요. 입대일, 전역일, 복무 부대, 계급 등이 기재되고 취업, 보훈 혜택 신청 시 병역 이행 증명이 필요할 때 사용해요.",
  "category": "민원·행정",
  "source": "정부24",
  "sourceUrl": "https://www.gov.kr",
  "downloads": {},
  "downloadNames": {},
  "previewDataKey": "DEFAULT",
  "relatedArticle": "/w/병적증명서",
  "tips": [
    "정부24에서 무료 즉시 발급 가능해요",
    "병역미필자도 병역판정검사 기록 확인 가능해요",
    "영문 증명서도 발급되니 해외 취업 시 유용해요"
  ],
  "faq": [
    {"question": "병적증명서 온라인 발급 되나요?", "answer": "네, 정부24에서 간편인증으로 바로 발급돼요. 수수료 무료이고 PDF로 저장하거나 출력 가능해요."},
    {"question": "병적증명서 전역증명서 차이는?", "answer": "전역증명서는 전역 직후 부대에서 받는 서류고, 병적증명서는 이후 필요할 때마다 정부24에서 발급받는 공식 증명서예요. 효력은 동일해요."},
    {"question": "병적증명서 미필자도 발급되나요?", "answer": "네, 병역미필자도 병역판정검사 결과나 면제 사유가 기재된 병적증명서를 발급받을 수 있어요. 취업이나 공공기관 제출용으로 쓸 수 있어요."}
  ],
  "createdAt": "2026-01-17"
}